mcp_actions_adapter/__init__.py
mcp_actions_adapter/config.py
mcp_actions_adapter/lifespan.py
mcp_actions_adapter/main.py
mcp_actions_adapter/modeler.py
mcp_actions_adapter-0.1.0.dist-info/METADATA
mcp_actions_adapter-0.1.0.dist-info/WHEEL
mcp_actions_adapter-0.1.0.dist-info/entry_points.txt
mcp_actions_adapter-0.1.0.dist-info/licenses/LICENSE
mcp_actions_adapter-0.1.0.dist-info/RECORD
