Metadata-Version: 2.4
Name: mcp-actions-adapter
Version: 0.1.0
Summary: A simple adapter to convert a MCP server to a GPT actions compatible API
Author-email: TerminalMan <84923604+SecretiveShell@users.noreply.github.com>
License-File: LICENSE
Requires-Python: >=3.11
Requires-Dist: fastapi>=0.115.10
Requires-Dist: loguru>=0.7.3
Requires-Dist: mcp==1.0.0
Requires-Dist: pydantic>=2.10.6
Requires-Dist: uvicorn>=0.34.0
